MetasploitManual/README.md
MetasploitManual/__init__.py
MetasploitManual/__main__.py
MetasploitManual/file.epub
MetasploitManual/index.html
MetasploitManual/css/__init__.py
MetasploitManual/css/annotations.css
MetasploitManual/css/main.css
MetasploitManual/css/normalize.css
MetasploitManual/css/popup.css
MetasploitManual/font/__init__.py
MetasploitManual/font/fontello.eot
MetasploitManual/font/fontello.svg
MetasploitManual/font/fontello.ttf
MetasploitManual/font/fontello.woff
MetasploitManual/img/__init__.py
MetasploitManual/img/annotator-glyph-sprite.png
MetasploitManual/img/annotator-icon-sprite.png
MetasploitManual/img/apple-touch-icon.png
MetasploitManual/img/cancelfullscreen.png
MetasploitManual/img/close.png
MetasploitManual/img/fullscreen.png
MetasploitManual/img/loader.gif
MetasploitManual/img/menu-icon.png
MetasploitManual/img/save.png
MetasploitManual/img/saved.png
MetasploitManual/img/settings-s.png
MetasploitManual/img/settings.png
MetasploitManual/img/star.png
MetasploitManual/js/__init__.py
MetasploitManual/js/epub.js
MetasploitManual/js/epub.min.js
MetasploitManual/js/epub.min.map
MetasploitManual/js/hooks.min.js
MetasploitManual/js/hooks.min.map
MetasploitManual/js/reader.js
MetasploitManual/js/reader.js.map
MetasploitManual/js/reader.min.js
MetasploitManual/js/reader.min.map
MetasploitManual/js/hooks/__init__.py
MetasploitManual/js/hooks/extensions/__init__.py
MetasploitManual/js/hooks/extensions/highlight.js
MetasploitManual/js/libs/__init__.py
MetasploitManual/js/libs/jquery.min.js
MetasploitManual/js/libs/localforage.min.js
MetasploitManual/js/libs/screenfull.js
MetasploitManual/js/libs/screenfull.min.js
MetasploitManual/js/libs/zip.min.js
MetasploitManual/js/plugins/__init__.py
MetasploitManual/js/plugins/hypothesis.js
MetasploitManual/js/plugins/search.js
metasploit_manual-2024.2.29.0.dist-info/METADATA
metasploit_manual-2024.2.29.0.dist-info/WHEEL
metasploit_manual-2024.2.29.0.dist-info/entry_points.txt
metasploit_manual-2024.2.29.0.dist-info/top_level.txt
metasploit_manual-2024.2.29.0.dist-info/RECORD
